cloud_ssh_config/__init__.py
cloud_ssh_config/cloud_ssh_config
cloud_ssh_config/cloud/__init__.py
cloud_ssh_config/cloud/__init__.pyc
cloud_ssh_config/cloud/aws.py
cloud_ssh_config/cloud/aws.pyc
cloud_ssh_config/cloud/do.py
cloud_ssh_config/cloud/do.pyc
cloud_ssh_config/cloud/scaleway.py
cloud_ssh_config/cloud/scaleway.pyc
cloud_ssh_config/ssh_config/__init__.py
cloud_ssh_config/ssh_config/__init__.pyc
cloud_ssh_config/ssh_config/ssh_config.py
cloud_ssh_config/ssh_config/ssh_config.pyc
cloud_ssh_config-0.3.0.data/scripts/cloud_ssh_config
cloud_ssh_config-0.3.0.dist-info/LICENSE
cloud_ssh_config-0.3.0.dist-info/METADATA
cloud_ssh_config-0.3.0.dist-info/WHEEL
cloud_ssh_config-0.3.0.dist-info/top_level.txt
cloud_ssh_config-0.3.0.dist-info/RECORD
